jinja2_ext/__init__.py
jinja2_ext/filters.py
Jinja2_Ext-0.1.dist-info/LICENSE
Jinja2_Ext-0.1.dist-info/METADATA
Jinja2_Ext-0.1.dist-info/WHEEL
Jinja2_Ext-0.1.dist-info/top_level.txt
Jinja2_Ext-0.1.dist-info/RECORD
